chaosprom/__init__.py
chaosprom/probes.py
sky_chaostoolkit_prometheus-0.3.5.dist-info/LICENSE
sky_chaostoolkit_prometheus-0.3.5.dist-info/METADATA
sky_chaostoolkit_prometheus-0.3.5.dist-info/WHEEL
sky_chaostoolkit_prometheus-0.3.5.dist-info/top_level.txt
sky_chaostoolkit_prometheus-0.3.5.dist-info/RECORD
